ChangeLog
LICENSE
MANIFEST.in
README.md
README.txt
setup.py
sevencow.py
test.py
sevencow.egg-info/PKG-INFO
sevencow.egg-info/SOURCES.txt
sevencow.egg-info/dependency_links.txt
sevencow.egg-info/requires.txt
sevencow.egg-info/top_level.txt