Metadata-Version: 1.1
Name: sevencow
Version: 0.2.0
Summary: Yet another qiniu cloud storage Python SDK
Home-page: https://github.com/yueyoum/seven-cow
Author: Wang Chao
Author-email: yueyoum@gmail.com
License: BSD
Platform: UNKNOWN
Classifier: Development Status :: 4 - Beta
Classifier: Topic :: Internet
Classifier: License :: OSI Approved :: BSD License
Classifier: Operating System :: OS Independent
Classifier: Programming Language :: Python
